prophetess_netbox/__init__.py
prophetess_netbox/client.py
prophetess_netbox/exceptions.py
prophetess_netbox/loader.py
tests/__init__.py
tests/fixtures.py
tests/test_client.py
tests/test_loader.py
prophetess_netbox-0.3.5.dist-info/LICENSE
prophetess_netbox-0.3.5.dist-info/METADATA
prophetess_netbox-0.3.5.dist-info/WHEEL
prophetess_netbox-0.3.5.dist-info/entry_points.txt
prophetess_netbox-0.3.5.dist-info/top_level.txt
prophetess_netbox-0.3.5.dist-info/RECORD
