Metadata-Version: 2.1
Name: prophetess-netbox
Version: 0.3.5
Summary: Netbox plugin for Prophetess
Home-page: https://github.com/vapor-ware/prophetess-netbox
Author: Marco Ceppi
Author-email: marco@vapor.io
License: GNU General Public License v3.0
Platform: UNKNOWN
Classifier: Environment :: Plugins
Classifier: Programming Language :: Python :: 3
Classifier: License :: OSI Approved :: GNU General Public License v3 (GPLv3)
Classifier: Operating System :: OS Independent
Requires-Python: >=3.6
Requires-Dist: aionetbox
